{"is_source_file": true, "format": "Python", "description": "This source file defines authentication routes for user registration and login in a Flask-based web service, utilizing Flask-Smorest for API blueprinting and marshmallow schemas for data validation.", "external_files": ["../models", "../schemas", "../auth_utils"], "external_methods": ["db.session.add", "db.session.commit", "User.query.filter_by", "User.set_password", "User.check_password", "generate_jwt", "abort"], "published": ["blp"], "classes": [{"name": "Register", "description": "Handles user registration via POST request at /register."}, {"name": "Login", "description": "Handles user login via POST request at /login."}], "methods": [{"name": "post(self, login_data)", "description": "Processes registration or login data, interacts with User model, and returns appropriate success or error responses.", "scope": "Login", "scopeKind": "class"}, {"name": "post(self, user_data)", "scope": "Register", "scopeKind": "class", "description": "unavailable"}], "calls": ["User.query.filter_by", "user.set_password", "user.check_password", "generate_jwt", "db.session.add", "db.session.commit", "abort"], "search-terms": ["flask_smorest", "UserRegisterSchema", "UserLoginSchema", "generate_jwt", "auth"], "state": 2, "file_id": 11, "knowledge_revision": 23, "git_revision": "", "ctags": [{"_type": "tag", "name": "Login", "path": "/home/kavia/workspace/code-generation/note-manager-14038-14075/notes_backend/app/routes/auth.py", "pattern": "/^class Login(MethodView):$/", "language": "Python", "kind": "class"}, {"_type": "tag", "name": "Register", "path": "/home/kavia/workspace/code-generation/note-manager-14038-14075/notes_backend/app/routes/auth.py", "pattern": "/^class Register(MethodView):$/", "language": "Python", "kind": "class"}, {"_type": "tag", "name": "blp", "path": "/home/kavia/workspace/code-generation/note-manager-14038-14075/notes_backend/app/routes/auth.py", "pattern": "/^blp = Blueprint(\"Auth\", \"auth\", url_prefix=\"\\/api\\/auth\", description=\"User authentication route/", "language": "Python", "kind": "variable"}, {"_type": "tag", "name": "post", "path": "/home/kavia/workspace/code-generation/note-manager-14038-14075/notes_backend/app/routes/auth.py", "pattern": "/^    def post(self, login_data):$/", "language": "Python", "kind": "member", "signature": "(self, login_data)", "scope": "Login", "scopeKind": "class"}, {"_type": "tag", "name": "post", "path": "/home/kavia/workspace/code-generation/note-manager-14038-14075/notes_backend/app/routes/auth.py", "pattern": "/^    def post(self, user_data):$/", "language": "Python", "kind": "member", "signature": "(self, user_data)", "scope": "Register", "scopeKind": "class"}], "hash": "ad53c9bcce4e8f1082db4569025b490c", "format-version": 4, "code-base-name": "notes_backend", "filename": "notes_backend/app/routes/auth.py", "fields": [{"name": "blp = Blueprint(\"Auth\", \"auth\", url_prefix=\"\\/api\\/auth\", description=\"User authentication route/", "scope": "", "scopeKind": "", "description": "unavailable"}], "revision_history": [{"23": ""}]}